[
  {
    "key": "ap5_6",
    "wrappers": [
      "expansion-panel"
    ],
    "templateOptions": {
      "label": "5.6 Documentación adicional"
    },
    "fieldGroup": [
      {
        "template": "¿Dispone de alguna otra documentación adicional para su proyecto? (p.ej. referencias bibliográficas etc)"
      },
      {
        "key": "documentacionAdicional",
        "type": "documento",
        "templateOptions": {
          "label": "Indicar",
          "required": true,
          "options": [
            {
              "value": 0,
              "label": "No"
            },
            {
              "value": 16,
              "label": "Sí"
            }
          ]
        }
      },
      {
        "key": "documentacionAdicionalDescripcion",
        "type": "textarea",
        "hideExpression": "!model.documentacionAdicional || model.documentacionAdicional === 0",
        "templateOptions": {
          "label": "Especificar",
          "required": true,
          "autosize": true,
          "autosizeMinRows": "1",
          "autosizeMaxRows": "10"
        }
      }
    ]
  }
]